client/__init__.py
client/api.py
client/client.py
client/command_line.py
lotr_isaaktreat-0.0.2.dist-info/METADATA
lotr_isaaktreat-0.0.2.dist-info/WHEEL
lotr_isaaktreat-0.0.2.dist-info/entry_points.txt
lotr_isaaktreat-0.0.2.dist-info/license.md
lotr_isaaktreat-0.0.2.dist-info/top_level.txt
lotr_isaaktreat-0.0.2.dist-info/RECORD
